yolo2onnx_extended/__init__.py
yolo2onnx_extended/__main__.py
yolo2onnx_extended/cli.py
yolo2onnx_extended/exporter.py
yolo2onnx_extended/yolo2onnx.py
yolo2onnx_extended-0.2.2.dist-info/LICENSE
yolo2onnx_extended-0.2.2.dist-info/METADATA
yolo2onnx_extended-0.2.2.dist-info/WHEEL
yolo2onnx_extended-0.2.2.dist-info/entry_points.txt
yolo2onnx_extended-0.2.2.dist-info/top_level.txt
yolo2onnx_extended-0.2.2.dist-info/RECORD
