Metadata-Version: 2.1
Name: yolo2onnx_extended
Version: 0.2.2
Summary: YOLOv8 to ONNX Exporter with Pre and Post Processing
Author-email: Francisco Tendero <francisco.tendero@tdk.com>
Project-URL: Homepage, https://bitbucket.tdk-electronics.biz/scm/dsc/yolo2onnx-extended.git
Keywords: yolo,onnx,preprocessing,postprocessing
Classifier: Programming Language :: Python :: 3
Requires-Python: >=3.8
License-File: LICENSE
Requires-Dist: torch
Requires-Dist: torchaudio
Requires-Dist: torchvision
Requires-Dist: onnx
Requires-Dist: onnxruntime
Requires-Dist: onnxruntime-extensions
Requires-Dist: ultralytics
Requires-Dist: typer
Provides-Extra: dev
Requires-Dist: black; extra == "dev"
Requires-Dist: flake8; extra == "dev"
Provides-Extra: gpu
Requires-Dist: onnxruntime-gpu; extra == "gpu"
